micone/__init__.py
micone/cli.py
micone/conversion/__init__.py
micone/conversion/network_converter.py
micone/conversion/otu_converter.py
micone/conversion/taxmetadata_converter.py
micone/logging/__init__.py
micone/logging/logger.py
micone/main/__init__.py
micone/main/lineage.py
micone/main/network.py
micone/main/network_group.py
micone/main/otu.py
micone/micone.py
micone/pipelines/__init__.py
micone/pipelines/command.py
micone/pipelines/configs/denoise_cluster.config
micone/pipelines/configs/network_inference.config
micone/pipelines/configs/otu_processing.config
micone/pipelines/configs/process.config
micone/pipelines/configs/profiles.config
micone/pipelines/configs/sequence_processing.config
micone/pipelines/configs/tax_assignment.config
micone/pipelines/data/classifiers/gg_13_8_99_515_806.qza
micone/pipelines/data/databases/greengenes/gg_97/refseqs.qza
micone/pipelines/data/databases/greengenes/gg_97/taxonomy.qza
micone/pipelines/data/databases/ncbi/ncbi/refseqs.qza
micone/pipelines/data/databases/ncbi/ncbi/taxonomy.qza
micone/pipelines/data/qiime1_parameters.txt
micone/pipelines/envs/micone-cozine/env.yml
micone/pipelines/envs/micone-cozine/post_install.sh
micone/pipelines/envs/micone-dada2/env.yml
micone/pipelines/envs/micone-flashweave/env.yml
micone/pipelines/envs/micone-flashweave/post_install.sh
micone/pipelines/envs/micone-harmonies/env.yml
micone/pipelines/envs/micone-harmonies/post_install.sh
micone/pipelines/envs/micone-mldm/env.yml
micone/pipelines/envs/micone-mldm/post_install.sh
micone/pipelines/envs/micone-propr/env.yml
micone/pipelines/envs/micone-propr/post_install.sh
micone/pipelines/envs/micone-qiime2/env.yml
micone/pipelines/envs/micone-qiime2/post_install.sh
micone/pipelines/envs/micone-sparcc/env.yml
micone/pipelines/envs/micone-spieceasi/env.yml
micone/pipelines/envs/micone-spring/env.yml
micone/pipelines/envs/micone-spring/post_install.sh
micone/pipelines/functions/functions.nf
micone-0.15.0.dist-info/LICENSE
micone-0.15.0.dist-info/METADATA
micone-0.15.0.dist-info/WHEEL
micone-0.15.0.dist-info/entry_points.txt
micone-0.15.0.dist-info/RECORD
