Metadata-Version: 2.1
Name: micone
Version: 0.15.0
Summary: The Microbial Co-occurrence Network Explorer
Home-page: https://github.com/segrelab/MiCoNE
License: MIT
Author: Dileep Kishore
Author-email: dkishore@bu.edu
Requires-Python: >=3.11
Classifier: License :: OSI Approved :: MIT License
Classifier: Programming Language :: Python :: 3
Classifier: Programming Language :: Python :: 3.11
Provides-Extra: docs
Requires-Dist: Jinja2 (>=2.11.2,<3.0.0)
Requires-Dist: Sphinx (>=5.1.1,<6.0.0) ; extra == "docs"
Requires-Dist: biom-format (>=2.1.10,<3.0.0)
Requires-Dist: click (>=8.1.3,<9.0.0)
Requires-Dist: ete3 (>=3.1.2,<4.0.0)
Requires-Dist: h5py (>=3.1.0,<4.0.0)
Requires-Dist: halo (>=0.0.31,<0.0.32)
Requires-Dist: jinja2schema (>=0.1.4,<0.2.0)
Requires-Dist: loguru (>=0.5.3,<0.6.0)
Requires-Dist: markupsafe (==2.0.1)
Requires-Dist: matplotlib (>=3.3.3,<4.0.0)
Requires-Dist: networkx (>=2.5,<3.0)
Requires-Dist: numpy (>=1.19.4,<2.0.0)
Requires-Dist: pandas (>=1.2.0,<2.0.0)
Requires-Dist: schematics (>=2.1.0,<3.0.0)
Requires-Dist: simplejson (>=3.17.2,<4.0.0)
Requires-Dist: sphinx-rtd-theme (>=1.0.0,<2.0.0) ; extra == "docs"
Requires-Dist: statsmodels (==0.14.0)
Project-URL: Documentation, https://micone.readthedocs.io/en/latest
